koml/__init__.py
koml/config.py
koml/koml_bot.py
koml/brain/__init__.py
koml/brain/blank_arg.py
koml/brain/errors.py
koml/brain/pattern_matcher.py
koml/brain/pattern_rule.py
koml/brain/template_solver.py
koml/brain/utils.py
koml/context/__init__.py
koml/context/chat.py
koml/context/context.py
koml/customize/__init__.py
koml/customize/custom_bag.py
koml/customize/custom_function.py
koml/customize/errors.py
koml/customize/preprocessor.py
koml/parser/__init__.py
koml/parser/create_parser.py
koml/parser/errors.py
koml/parser/koml_handler.py
koml/parser/koml_state.py
koml/parser/raw_tag.py
koml/parser/resolver.py
koml/parser/utils.py
koml/tags/__init__.py
koml/tags/abstracts.py
koml/tags/case.py
koml/tags/errors.py
koml/tags/items.py
koml/tags/leafs.py
koml/tags/nodes.py
koml/tags/sections.py
koml/tags/utils.py
korean_rule_helper/parser/__init__.py
korean_rule_helper/parser/mecab.py
korean_rule_helper/parser/parser.py
korean_rule_helper/parser/tag.py
koml-1.0.0.dist-info/METADATA
koml-1.0.0.dist-info/WHEEL
koml-1.0.0.dist-info/top_level.txt
koml-1.0.0.dist-info/RECORD
