Metadata-Version: 2.1
Name: koml
Version: 1.0.0
Summary: 누구나 쉽게 한국어챗봇을 만들 수 있게
Home-page: https://github.com/5yearsKim/KoML
Author: 5yearsKim
Author-email: hypothesis22@gmail.com
License: UNKNOWN
Platform: UNKNOWN
Requires-Dist: hgtk (==0.1.3)
Requires-Dist: six (==1.16.0)
Requires-Dist: korean-rule-helper (==0.0.8)
